ros_launch_analyzer/__init__.py
ros_launch_analyzer/_version.py
ros_launch_analyzer/analyzer.py
ros_launch_analyzer/cli.py
ros_launch_analyzer-0.1.1.dist-info/LICENSE
ros_launch_analyzer-0.1.1.dist-info/METADATA
ros_launch_analyzer-0.1.1.dist-info/WHEEL
ros_launch_analyzer-0.1.1.dist-info/entry_points.txt
ros_launch_analyzer-0.1.1.dist-info/RECORD
