Metadata-Version: 2.3
Name: ros-launch-analyzer
Version: 0.1.1
Summary: 
Author: Daisuke Sato
Author-email: tiryoh@gmail.com
Requires-Python: >=3.8.1,<4.0.0
Classifier: Programming Language :: Python :: 3
Classifier: Programming Language :: Python :: 3.9
Classifier: Programming Language :: Python :: 3.10
Classifier: Programming Language :: Python :: 3.11
Classifier: Programming Language :: Python :: 3.12
Classifier: Programming Language :: Python :: 3.13
Requires-Dist: graphviz (>=0.20.3,<0.21.0)
Project-URL: Repository, https://github.com/Tiryoh/ros-launch-analyzer
